pystreamapi/__init__.py
pystreamapi/__iterate.py
pystreamapi/__optional.py
pystreamapi/__stream.py
pystreamapi/__stream_converter.py
pystreamapi/_itertools/__init__.py
pystreamapi/_itertools/tools.py
pystreamapi/_lazy/__init__.py
pystreamapi/_lazy/process.py
pystreamapi/_lazy/queue.py
pystreamapi/_parallel/__init__.py
pystreamapi/_parallel/fork_and_join.py
pystreamapi/_parallel/parallelizer.py
pystreamapi/_streams/__base_stream.py
pystreamapi/_streams/__init__.py
pystreamapi/_streams/__parallel_stream.py
pystreamapi/_streams/__sequential_stream.py
pystreamapi/_streams/error/__error.py
pystreamapi/_streams/error/__levels.py
pystreamapi/_streams/error/__sentinel.py
pystreamapi/_streams/numeric/__numeric_base_stream.py
pystreamapi/_streams/numeric/__parallel_numeric_stream.py
pystreamapi/_streams/numeric/__sequential_numeric_stream.py
pystreamapi/conditions/__init__.py
pystreamapi/conditions/combiners.py
pystreamapi/conditions/date.py
pystreamapi/conditions/numeric.py
pystreamapi/conditions/string.py
pystreamapi/conditions/types.py
pystreamapi/loaders/__csv/__csv_loader.py
pystreamapi/loaders/__csv/__init__.py
pystreamapi/loaders/__init__.py
pystreamapi/loaders/__json/__init__.py
pystreamapi/loaders/__json/__json_loader.py
pystreamapi/loaders/__lazy_file_iterable.py
pystreamapi/loaders/__loader_utils.py
pystreamapi/loaders/__xml/__init__.py
pystreamapi/loaders/__xml/__xml_loader.py
pystreamapi/loaders/__yaml/__init__.py
pystreamapi/loaders/__yaml/__yaml_loader.py
streams_py-1.3.0.dist-info/LICENSE
streams_py-1.3.0.dist-info/METADATA
streams_py-1.3.0.dist-info/WHEEL
streams_py-1.3.0.dist-info/RECORD
