Metadata-Version: 2.1
Name: streams.py
Version: 1.3.0
Summary: A stream library for Python inspired by Java Stream API
Home-page: https://github.com/PickwickSoft/pystreamapi
License: GPL-3.0-or-later
Keywords: streams,parallel,data
Author: Stefan Garlonta
Author-email: stefan@pickwicksoft.org
Requires-Python: >=3.7,<4.0
Classifier: License :: OSI Approved :: GNU General Public License v3 or later (GPLv3+)
Classifier: Programming Language :: Python :: 3
Classifier: Programming Language :: Python :: 3.7
Classifier: Programming Language :: Python :: 3.8
Classifier: Programming Language :: Python :: 3.9
Classifier: Programming Language :: Python :: 3.10
Classifier: Programming Language :: Python :: 3.11
Classifier: Programming Language :: Python :: 3.12
Provides-Extra: all
Provides-Extra: xml-loader
Provides-Extra: yaml-loader
Requires-Dist: defusedxml (>=0.7,<0.8) ; extra == "xml-loader" or extra == "all"
Requires-Dist: joblib (>=1.2,<=1.4.2)
Requires-Dist: pyyaml (>=6.0.1,<7.0.0) ; extra == "yaml-loader" or extra == "all"
Project-URL: Repository, https://github.com/PickwickSoft/pystreamapi
